subprocessor.py
subprocessor-1.0.0.dist-info/LICENSE
subprocessor-1.0.0.dist-info/METADATA
subprocessor-1.0.0.dist-info/WHEEL
subprocessor-1.0.0.dist-info/top_level.txt
subprocessor-1.0.0.dist-info/RECORD
