Metadata-Version: 1.1
Name: subprocessor
Version: 1.0.0
Summary: Run a subprocess with callbacks
Home-page: https://github.com/rec/subprocessor
Author: Tom Ritchford
Author-email: tom@swirly.com
License: MIT
Keywords: backups
Platform: UNKNOWN
Classifier: Development Status :: 4 - Beta
Classifier: Programming Language :: Python :: 3.5
Classifier: Programming Language :: Python :: 3.6
Classifier: Programming Language :: Python :: 3.7
Classifier: Programming Language :: Python :: 3.8
Classifier: Intended Audience :: Developers
Classifier: License :: OSI Approved :: MIT License
Classifier: Topic :: Software Development :: Libraries
Classifier: Topic :: Utilities
